ltst_midge-0.0.3.dist-info/LICENSE.txt
ltst_midge-0.0.3.dist-info/METADATA
ltst_midge-0.0.3.dist-info/RECORD
ltst_midge-0.0.3.dist-info/WHEEL
ltst_midge-0.0.3.dist-info/top_level.txt
midge/__init__.py
midge/actions.py
